{
  "applications": [
    {
      "id": "cloud_dm",
      "name": "Cloud DM",
      "version": "6.4",
      "vendor": "Intel",
      "description": "Optimized methodical matrices",
      "categoryId": "platform",
      "applicationSize": "Small",
      "updatedAt": "2018-05-07T01:56:53.033Z",
      "updatedBy": "usr/0375762c-f85e-4aac-bb13-2e504c45a4e0",
      "status": "Standard",
      "sme_email": "Jo.Talkington@memento.net.au",
      "end_of_maintenance": "24/11/17",
      "months_to_renew_support": 14,
      "department": "Support",
      "hostedtype": "OnPremise3",
      "investment_24m": "654",
      "support_cost": "86",
      "end_of_life": "16/6/18",
      "deployment_date": "27/9/03",
      "vendor_contact_name": "Wendeline Readwing",
      "vendor_phone": "+7 832 959 4879",
      "investment_number": 407,
      "type": "InHouseDev",
      "vendor_email": "Wendeline.Readwing@Intel.com",
      "licensing_cost": "161",
      "integrations": [
        {
          "id": "int-248",
          "name": "INT-248",
          "version": "2.34",
          "description": "Phasellus in felis. Donec semper sapien a libero. Nam dui.",
          "payload": "Supplier Name / Pick Location",
          "targetApplicationId": "veribet",
          "categoryId": "webmethods",
          "status": "Standard",
          "department": "Integration",
          "complexity": "High",
          "golive_date": "18/12/16",
          "pattern": "Scatter Gather",
          "last_deployment_date": "1/11/16",
          "datacentre": "Asia Pacific (Melbourne)",
          "sme_name": "Guenna Kix",
          "logical_server": "CLOUD-A2A",
          "sme_email": "gkixg@memento.net.au"
        }
      ]
    }
  ]
}